visidata/__init__.py
visidata/__main__.py
visidata/_input.py
visidata/_open.py
visidata/_types.py
visidata/_urlcache.py
visidata/aggregators.py
visidata/basesheet.py
visidata/bezier.py
visidata/canvas.py
visidata/canvas_text.py
visidata/choose.py
visidata/clean_names.py
visidata/clipboard.py
visidata/cliptext.py
visidata/cmdlog.py
visidata/color.py
visidata/column.py
visidata/ddwplay.py
visidata/deprecated.py
visidata/editor.py
visidata/errors.py
visidata/expr.py
visidata/extensible.py
visidata/form.py
visidata/freqtbl.py
visidata/fuzzymatch.py
visidata/graph.py
visidata/guide.py
visidata/help.py
visidata/hint.py
visidata/indexsheet.py
visidata/input_history.py
visidata/interface.py
visidata/keys.py
visidata/macos.py
visidata/macros.py
visidata/main.py
visidata/mainloop.py
visidata/memory.py
visidata/menu.py
visidata/metasheets.py
visidata/modify.py
visidata/motd.py
visidata/mouse.py
visidata/movement.py
visidata/optionssheet.py
visidata/path.py
visidata/pivot.py
visidata/plugins.py
visidata/pyobj.py
visidata/rename_col.py
visidata/save.py
visidata/search.py
visidata/selection.py
visidata/settings.py
visidata/sheets.py
visidata/shell.py
visidata/sidebar.py
visidata/sort.py
visidata/statusbar.py
visidata/stored_list.py
visidata/text_source.py
visidata/textsheet.py
visidata/theme.py
visidata/threads.py
visidata/tuiwin.py
visidata/type_currency.py
visidata/type_date.py
visidata/type_floatsi.py
visidata/undo.py
visidata/utils.py
visidata/vdobj.py
visidata/windows.py
visidata/wrappers.py
visidata/apps/__init__.py
visidata/apps/vdsql/__about__.py
visidata/apps/vdsql/__init__.py
visidata/apps/vdsql/__main__.py
visidata/apps/vdsql/_ibis.py
visidata/apps/vdsql/bigquery.py
visidata/apps/vdsql/clickhouse.py
visidata/apps/vdsql/setup.py
visidata/apps/vdsql/snowflake.py
visidata/apps/vgit/__init__.py
visidata/apps/vgit/__main__.py
visidata/apps/vgit/abort.py
visidata/apps/vgit/blame.py
visidata/apps/vgit/branch.py
visidata/apps/vgit/config.py
visidata/apps/vgit/diff.py
visidata-3.3.dist-info/LICENSE.gpl3
visidata-3.3.dist-info/METADATA
visidata-3.3.dist-info/WHEEL
visidata-3.3.dist-info/entry_points.txt
visidata-3.3.dist-info/top_level.txt
visidata-3.3.dist-info/RECORD
