Metadata-Version: 2.1
Name: visidata
Version: 3.3
Summary: terminal interface for exploring and arranging tabular data
Home-page: https://visidata.org
Download-URL: https://github.com/saulpw/visidata/tarball/3.3
Author: Saul Pwanson
Author-email: visidata@saul.pw
License: GPLv3
Keywords: console tabular data spreadsheet terminal viewer textpunkcurses csv hdf5 h5 xlsx excel tsv
Classifier: Development Status :: 5 - Production/Stable
Classifier: Environment :: Console
Classifier: Environment :: Console :: Curses
Classifier: Intended Audience :: Developers
Classifier: Intended Audience :: Science/Research
Classifier: Intended Audience :: System Administrators
Classifier: License :: OSI Approved :: GNU General Public License v3 (GPLv3)
Classifier: Operating System :: OS Independent
Classifier: Programming Language :: Python :: 3
Classifier: Topic :: Database :: Front-Ends
Classifier: Topic :: Scientific/Engineering
Classifier: Topic :: Office/Business :: Financial :: Spreadsheet
Classifier: Topic :: Scientific/Engineering :: Visualization
Classifier: Topic :: Utilities
Requires-Python: >=3.8
License-File: LICENSE.gpl3
Requires-Dist: python-dateutil
Requires-Dist: windows-curses (>=2.4.1) ; platform_system == "Windows"
Requires-Dist: importlib-resources ; python_version < "3.9"
Requires-Dist: standard-mailcap ; python_version >= "3.13"
Provides-Extra: all
Requires-Dist: python-dateutil ; extra == 'all'
Requires-Dist: requests ; extra == 'all'
Requires-Dist: lxml ; extra == 'all'
Requires-Dist: openpyxl (>=2.4) ; extra == 'all'
Requires-Dist: xlrd ; extra == 'all'
Requires-Dist: xlwt ; extra == 'all'
Requires-Dist: h5py ; extra == 'all'
Requires-Dist: psycopg2-binary ; extra == 'all'
Requires-Dist: boto3 ; extra == 'all'
Requires-Dist: pyshp ; extra == 'all'
Requires-Dist: mapbox-vector-tile ; extra == 'all'
Requires-Dist: pypng ; extra == 'all'
Requires-Dist: fonttools ; extra == 'all'
Requires-Dist: sas7bdat ; extra == 'all'
Requires-Dist: xport (>=3) ; extra == 'all'
Requires-Dist: PyYAML (>=5.1) ; extra == 'all'
Requires-Dist: dpkt ; extra == 'all'
Requires-Dist: dnslib ; extra == 'all'
Requires-Dist: namestand ; extra == 'all'
Requires-Dist: datapackage ; extra == 'all'
Requires-Dist: pdfminer.six ; extra == 'all'
Requires-Dist: tabula ; extra == 'all'
Requires-Dist: vobject ; extra == 'all'
Requires-Dist: tabulate ; extra == 'all'
Requires-Dist: wcwidth ; extra == 'all'
Requires-Dist: zstandard ; extra == 'all'
Requires-Dist: odfpy ; extra == 'all'
Requires-Dist: urllib3 ; extra == 'all'
Requires-Dist: seaborn ; extra == 'all'
Requires-Dist: matplotlib ; extra == 'all'
Requires-Dist: sh ; extra == 'all'
Requires-Dist: psutil ; extra == 'all'
Requires-Dist: numpy ; extra == 'all'
Requires-Dist: pyconll ; extra == 'all'
Requires-Dist: msgpack ; extra == 'all'
Requires-Dist: brotli ; extra == 'all'
Requires-Dist: fecfile ; extra == 'all'
Requires-Dist: requests-cache ; extra == 'all'
Requires-Dist: beautifulsoup4 ; extra == 'all'
Requires-Dist: Faker ; extra == 'all'
Requires-Dist: praw ; extra == 'all'
Requires-Dist: matrix-client ; extra == 'all'
Requires-Dist: zulip ; extra == 'all'
Requires-Dist: pyairtable ; extra == 'all'
Requires-Dist: pandas (>=1.0.5) ; (python_version < "3.11") and extra == 'all'
Requires-Dist: tomli ; (python_version < "3.11") and extra == 'all'
Requires-Dist: backports.zoneinfo ; (python_version < "3.9") and extra == 'all'
Requires-Dist: pyarrow-hotfix ; (python_version <= "3.7") and extra == 'all'
Requires-Dist: pyarrow ; (python_version <= "3.7") and extra == 'all'
Requires-Dist: pandas (>=1.5.3) ; (python_version >= "3.11") and extra == 'all'
Requires-Dist: pyarrow (>=14.0.1) ; (python_version >= "3.8") and extra == 'all'
Provides-Extra: test
Requires-Dist: brotli ; extra == 'test'
Requires-Dist: dnslib ; extra == 'test'
Requires-Dist: dpkt ; extra == 'test'
Requires-Dist: fecfile ; extra == 'test'
Requires-Dist: Faker ; extra == 'test'
Requires-Dist: h5py ; extra == 'test'
Requires-Dist: lxml ; extra == 'test'
Requires-Dist: msgpack ; extra == 'test'
Requires-Dist: odfpy ; extra == 'test'
Requires-Dist: openpyxl ; extra == 'test'
Requires-Dist: pandas (>=1.5.3) ; extra == 'test'
Requires-Dist: pyarrow ; extra == 'test'
Requires-Dist: pyconll ; extra == 'test'
Requires-Dist: pypng ; extra == 'test'
Requires-Dist: pytest ; extra == 'test'
Requires-Dist: PyYAML (>=5.1) ; extra == 'test'
Requires-Dist: tabulate ; extra == 'test'
Requires-Dist: tomli ; extra == 'test'
Requires-Dist: wcwidth ; extra == 'test'
Requires-Dist: xport (>=3.0) ; extra == 'test'
Provides-Extra: windows-curses
Requires-Dist: windows-curses (>=2.4.1) ; (platform_system == "Windows") and extra == 'windows-curses'
